MANIFEST.in
README.rst
setup.cfg
setup.py
NanoSV.egg-info/PKG-INFO
NanoSV.egg-info/SOURCES.txt
NanoSV.egg-info/dependency_links.txt
NanoSV.egg-info/entry_points.txt
NanoSV.egg-info/requires.txt
NanoSV.egg-info/top_level.txt
nanosv/NanoSV.py
nanosv/__init__.py
nanosv/config.ini
nanosv/version.py
nanosv/bedfiles/human_hg19.bed
nanosv/classes/__init__.py
nanosv/classes/breakpoint.py
nanosv/classes/read.py
nanosv/classes/segment.py
nanosv/classes/sv.py
nanosv/classes/variant.py
nanosv/utils/__init__.py
nanosv/utils/coverage.py
nanosv/utils/create_vcf.py
nanosv/utils/parse_bam.py
nanosv/utils/parse_breakpoints.py
nanosv/utils/parse_reads.py
nanosv/utils/parse_svs.py
nanosv/utils/phasing.py