Metadata-Version: 1.1
Name: NanoSV
Version: 1.2.0
Summary: Structural variation detection tool for Oxford Nanopore data.
Home-page: https://github.com/mroosmalen/nanosv
Author: Mark van Roosmalen
Author-email: m.vanroosmalen-2@umcutrecht.nl
License: MIT
Keywords: nanosv sv-caller nanopore
Platform: UNKNOWN
Classifier: Development Status :: 4 - Beta
Classifier: Intended Audience :: Science/Research
Classifier: License :: OSI Approved :: MIT License
Classifier: Programming Language :: Python :: 3
Classifier: Topic :: Scientific/Engineering :: Bio-Informatics
